myopy/__init__.py
myopy/pyfile.py
myopy/utils.py
myopy-1.1.2.dist-info/LICENSE
myopy-1.1.2.dist-info/WHEEL
myopy-1.1.2.dist-info/METADATA
myopy-1.1.2.dist-info/RECORD
