Metadata-Version: 2.1
Name: myopy
Version: 1.1.2
Summary: myopy, run blind python files.
Home-page: https://github.com/loiccoyle/myopy
License: MIT
Keywords: config,source
Author: Loic Coyle
Author-email: loic.coyle@hotmail.fr
Requires-Python: >=3.6,<4.0
Classifier: License :: OSI Approved :: MIT License
Classifier: Programming Language :: Python :: 3
Classifier: Programming Language :: Python :: 3.6
Classifier: Programming Language :: Python :: 3.7
Classifier: Programming Language :: Python :: 3.8
